[
  {
    "title": "On My Wife's Birth-Day"
  },
  {
    "title": "Jubilate Agno: Fragment B, Part 1"
  },
  {
    "title": "Jubilate Agno: Fragment C"
  },
  {
    "title": "Jubilate Agno: Fragment A"
  },
  {
    "title": "Jubilate Agno (excerpt)"
  },
  {
    "title": "from Jubilate Agno, Fragment B, lines 695-768"
  },
  {
    "title": "Jubilate Agno: Fragment D"
  },
  {
    "title": "For I Will Consider My Cat Jeoffry (excerpt, Jubilate Agno)"
  },
  {
    "title": "Jubilate Agno: Fragment B, Part 4"
  },
  {
    "title": "Jubilate Agno: Fragment B, Part 3"
  },
  {
    "title": "A Song To David"
  }
]