[
  {
    "title": "Ballad"
  },
  {
    "title": "Song"
  },
  {
    "title": "Summer Evening"
  },
  {
    "title": "What is Life?"
  },
  {
    "title": "The Maid Of Ocram or, Lord Gregory"
  },
  {
    "title": "The Gipsy's Camp"
  },
  {
    "title": "Impromptu"
  },
  {
    "title": "The Wood-cutter's Night Song"
  },
  {
    "title": "Song"
  },
  {
    "title": "In Hilly-Wood"
  },
  {
    "title": "To Anna Three Years Old"
  },
  {
    "title": "From \"The Parish: A Satire\""
  },
  {
    "title": "Nobody Cometh to Woo"
  },
  {
    "title": "Early Nightingale"
  },
  {
    "title": "Ploughman Singing"
  },
  {
    "title": "Spring's Messengers"
  },
  {
    "title": "Letter in Verse"
  },
  {
    "title": "Firwood"
  },
  {
    "title": "Grasshoppers"
  },
  {
    "title": "Field Path"
  },
  {
    "title": "Idle Fame"
  },
  {
    "title": "Death"
  },
  {
    "title": "Rural Morning"
  },
  {
    "title": "The Cross Roads; or, The Haymaker's Story"
  },
  {
    "title": "The Ants"
  },
  {
    "title": "Distant Hills"
  },
  {
    "title": "The Stranger"
  },
  {
    "title": "Song's Eternity"
  },
  {
    "title": "The Old Cottagers"
  },
  {
    "title": "Young Lambs"
  },
  {
    "title": "Winter Walk"
  },
  {
    "title": "The Soldier"
  },
  {
    "title": "Snow Storm"
  },
  {
    "title": "Country Letter"
  },
  {
    "title": "From \"January\""
  },
  {
    "title": "November"
  },
  {
    "title": "The Fens"
  },
  {
    "title": "Spear Thistle"
  },
  {
    "title": "Approaching Night"
  },
  {
    "title": "Farewell and Defiance to Love"
  },
  {
    "title": "To John Milton \"From his honoured friend, William Davenant\""
  },
  {
    "title": "The Vanities of Life"
  },
  {
    "title": "Death"
  },
  {
    "title": "The Fallen Elm"
  },
  {
    "title": "Sport in the Meadows"
  },
  {
    "title": "Autumn"
  },
  {
    "title": "A World for Love"
  },
  {
    "title": "Love"
  },
  {
    "title": "Nature's Hymn to the Deity"
  },
  {
    "title": "Decay"
  },
  {
    "title": "The Cellar Door"
  },
  {
    "title": "Remembrances"
  },
  {
    "title": "Sudden Shower"
  },
  {
    "title": "The Flitting"
  },
  {
    "title": "The Cottager"
  },
  {
    "title": "Insects"
  },
  {
    "title": "Evening Primrose"
  },
  {
    "title": "The Shepherd's Tree"
  },
  {
    "title": "Wild Bees"
  },
  {
    "title": "The Firetail's Nest"
  },
  {
    "title": "The Fear of Flowers"
  },
  {
    "title": "Summer Evening"
  },
  {
    "title": "Emmonsail's Heath in Winter"
  },
  {
    "title": "Pleasures of Fancy"
  },
  {
    "title": "To Napoleon"
  },
  {
    "title": "The Skylark"
  },
  {
    "title": "The Flood"
  },
  {
    "title": "The Thrush's Nest"
  },
  {
    "title": "November"
  },
  {
    "title": "Earth's Eternity"
  },
  {
    "title": "Autumn"
  },
  {
    "title": "Signs of Winter"
  },
  {
    "title": "Nightwind"
  },
  {
    "title": "Birds in Alarm"
  },
  {
    "title": "Dyke Side"
  },
  {
    "title": "Badger"
  },
  {
    "title": "The Fox"
  },
  {
    "title": "The Vixen"
  },
  {
    "title": "Turkeys"
  },
  {
    "title": "The Poet's Death"
  },
  {
    "title": "The Beautiful Stranger"
  },
  {
    "title": "The Tramp"
  },
  {
    "title": "Farmer's Boy"
  },
  {
    "title": "Braggart"
  },
  {
    "title": "Sunday Dip"
  },
  {
    "title": "Merry Maid"
  },
  {
    "title": "Scandal"
  },
  {
    "title": "Quail's Nest"
  },
  {
    "title": "Market Day"
  },
  {
    "title": "Stonepit"
  },
  {
    "title": "\"The Lass With The Delicate Air\""
  },
  {
    "title": "The Lout"
  },
  {
    "title": "Hodge"
  },
  {
    "title": "Farm Breakfast"
  },
  {
    "title": "Love and Solitude"
  },
  {
    "title": "Gipsies"
  },
  {
    "title": "The Frightened Ploughman"
  },
  {
    "title": "Farewell"
  },
  {
    "title": "The Old Year"
  },
  {
    "title": "The Yellowhammer"
  },
  {
    "title": "Autumn"
  },
  {
    "title": "Song"
  },
  {
    "title": "The Winter's Come"
  },
  {
    "title": "Summer Winds"
  },
  {
    "title": "Bonny Lassie O!"
  },
  {
    "title": "Meet Me in the Green Glen"
  },
  {
    "title": "Love Cannot Die"
  },
  {
    "title": "Peggy"
  },
  {
    "title": "The Crow Sat on the Willow"
  },
  {
    "title": "Now is Past"
  },
  {
    "title": "Song"
  },
  {
    "title": "First Love"
  },
  {
    "title": "Mary Bayfield"
  },
  {
    "title": "The Maid of Jerusalem"
  },
  {
    "title": "Song"
  },
  {
    "title": "Thou Flower of Summer"
  },
  {
    "title": "The Swallow"
  },
  {
    "title": "The Sailor-Boy"
  },
  {
    "title": "The Sleep of Spring"
  },
  {
    "title": "Mary Bateman"
  },
  {
    "title": "Bonny Mary O!"
  },
  {
    "title": "Where She Told Her Love"
  },
  {
    "title": "Autumn"
  },
  {
    "title": "Invitation to Eternity"
  },
  {
    "title": "The Maple Tree"
  },
  {
    "title": "House or Window Flies"
  },
  {
    "title": "Dewdrops"
  },
  {
    "title": "Fragment"
  },
  {
    "title": "From \"A Rhapsody\""
  },
  {
    "title": "Secret Love"
  },
  {
    "title": "Bantry Bay"
  },
  {
    "title": "Peggy's the Lady of the Hall"
  },
  {
    "title": "I Dreamt of Robin"
  },
  {
    "title": "The Peasant Poet"
  },
  {
    "title": "To John Clare"
  },
  {
    "title": "Early Spring"
  },
  {
    "title": "Clock-a-Clay"
  },
  {
    "title": "Little Trotty Wagtail"
  },
  {
    "title": "Graves of Infants"
  },
  {
    "title": "The Dying Child"
  },
  {
    "title": "Love Lives Beyond the Tomb"
  },
  {
    "title": "I Am"
  },
  {
    "title": "Fragment"
  }
]